Metadata-Version: 1.1
Name: now
Version: 0.0.5
Summary: Record what you are doing SIMPLY from the command line
Home-page: https://github.com/sashahart/now
Author: Sasha Hart
Author-email: s@sashahart.net
License: MIT
Platform: UNKNOWN
Classifier: Development Status :: 3 - Alpha
Classifier: License :: OSI Approved :: MIT License
